{"nodes": [{"id": "e_loigmax_tracker_knowledge_brain_system_shared_collections_md", "label": "SHARED_COLLECTIONS.md", "file_type": "document", "source_file": "E:\\Loigmax\\Tracker\\knowledge_brain\\_SYSTEM\\SHARED_COLLECTIONS.md", "source_location": "L1"}, {"id": "system_shared_collections_system_module_dependencies", "label": "System Module Dependencies", "file_type": "document", "source_file": "E:\\Loigmax\\Tracker\\knowledge_brain\\_SYSTEM\\SHARED_COLLECTIONS.md", "source_location": "L1"}, {"id": "system_shared_collections_shared_collections_inbound_refs", "label": "Shared Collections (Inbound Refs)", "file_type": "document", "source_file": "E:\\Loigmax\\Tracker\\knowledge_brain\\_SYSTEM\\SHARED_COLLECTIONS.md", "source_location": "L3"}, {"id": "system_shared_collections_dynamic_status_system_added_2026_06_10", "label": "Dynamic Status System (added 2026-06-10)", "file_type": "document", "source_file": "E:\\Loigmax\\Tracker\\knowledge_brain\\_SYSTEM\\SHARED_COLLECTIONS.md", "source_location": "L29"}, {"id": "system_shared_collections_models_with_both_status_metastatus", "label": "Models with both `status` + `metaStatus`", "file_type": "document", "source_file": "E:\\Loigmax\\Tracker\\knowledge_brain\\_SYSTEM\\SHARED_COLLECTIONS.md", "source_location": "L38"}, {"id": "system_shared_collections_statusconfig_seed_run_once_per_env", "label": "StatusConfig seed (run once per env)", "file_type": "document", "source_file": "E:\\Loigmax\\Tracker\\knowledge_brain\\_SYSTEM\\SHARED_COLLECTIONS.md", "source_location": "L49"}, {"id": "system_shared_collections_codeblock_1", "label": "code:block1 (node src/scripts/seedStatusConfigs.js)", "file_type": "document", "source_file": "E:\\Loigmax\\Tracker\\knowledge_brain\\_SYSTEM\\SHARED_COLLECTIONS.md", "source_location": "L50"}], "edges": [{"source": "e_loigmax_tracker_knowledge_brain_system_shared_collections_md", "target": "system_shared_collections_system_module_dependencies", "relation": "contains", "confidence": "EXTRACTED", "source_file": "E:\\Loigmax\\Tracker\\knowledge_brain\\_SYSTEM\\SHARED_COLLECTIONS.md", "source_location": "L1", "weight": 1.0}, {"source": "system_shared_collections_system_module_dependencies", "target": "system_shared_collections_shared_collections_inbound_refs", "relation": "contains", "confidence": "EXTRACTED", "source_file": "E:\\Loigmax\\Tracker\\knowledge_brain\\_SYSTEM\\SHARED_COLLECTIONS.md", "source_location": "L3", "weight": 1.0}, {"source": "system_shared_collections_system_module_dependencies", "target": "system_shared_collections_dynamic_status_system_added_2026_06_10", "relation": "contains", "confidence": "EXTRACTED", "source_file": "E:\\Loigmax\\Tracker\\knowledge_brain\\_SYSTEM\\SHARED_COLLECTIONS.md", "source_location": "L29", "weight": 1.0}, {"source": "system_shared_collections_dynamic_status_system_added_2026_06_10", "target": "system_shared_collections_models_with_both_status_metastatus", "relation": "contains", "confidence": "EXTRACTED", "source_file": "E:\\Loigmax\\Tracker\\knowledge_brain\\_SYSTEM\\SHARED_COLLECTIONS.md", "source_location": "L38", "weight": 1.0}, {"source": "system_shared_collections_dynamic_status_system_added_2026_06_10", "target": "system_shared_collections_statusconfig_seed_run_once_per_env", "relation": "contains", "confidence": "EXTRACTED", "source_file": "E:\\Loigmax\\Tracker\\knowledge_brain\\_SYSTEM\\SHARED_COLLECTIONS.md", "source_location": "L49", "weight": 1.0}, {"source": "system_shared_collections_statusconfig_seed_run_once_per_env", "target": "system_shared_collections_codeblock_1", "relation": "contains", "confidence": "EXTRACTED", "source_file": "E:\\Loigmax\\Tracker\\knowledge_brain\\_SYSTEM\\SHARED_COLLECTIONS.md", "source_location": "L50", "weight": 1.0}], "input_tokens": 0, "output_tokens": 0}